README.md
setup.py
xbos/__init__.py
xbos.egg-info/PKG-INFO
xbos.egg-info/SOURCES.txt
xbos.egg-info/dependency_links.txt
xbos.egg-info/not-zip-safe
xbos.egg-info/requires.txt
xbos.egg-info/top_level.txt
xbos/devices/__init__.py
xbos/devices/demand_response.py
xbos/devices/demand_response_confirmed.py
xbos/devices/demand_response_forecast.py
xbos/devices/evse.py
xbos/devices/light.py
xbos/devices/meter.py
xbos/devices/occupancy_sensor.py
xbos/devices/plug.py
xbos/devices/pricing.py
xbos/devices/pv_meter.py
xbos/devices/temperature_sensor.py
xbos/devices/thermostat.py
xbos/devices/weather_station.py
xbos/devices/window.py
xbos/services/__init__.py
xbos/services/brick.py
xbos/services/data.capnp
xbos/services/hod.py
xbos/services/mdal.py
xbos/services/pundat.py
xbos/services/t.py
xbos/util/__init__.py
xbos/util/util.py