Metadata-Version: 1.0
Name: xbos
Version: 0.0.34
Summary: Aggregate wrapper for XBOS services and devices
Home-page: https://github.com/SoftwareDefinedBuildings/XBOS
Author: Gabe Fierro
Author-email: gtfierro@cs.berkeley.edu
License: UNKNOWN
Platform: UNKNOWN
